open_mcp/__init__.py
open_mcp/py.typed
open_mcp/cli/__init__.py
open_mcp/cli/main.py
open_mcp/client/__init__.py
open_mcp/client/mcp_client.py
open_mcp/models/__init__.py
open_mcp/models/base.py
open_mcp/models/messages.py
open_mcp/models/protocol.py
open_mcp/server/__init__.py
open_mcp/server/mcp_server.py
open_mcp/utils/__init__.py
open_mcp/utils/logging.py
open_mcp/utils/validation.py
open_mcp_protocol-0.0.1.dist-info/METADATA
open_mcp_protocol-0.0.1.dist-info/WHEEL
open_mcp_protocol-0.0.1.dist-info/entry_points.txt
open_mcp_protocol-0.0.1.dist-info/licenses/LICENSE
open_mcp_protocol-0.0.1.dist-info/RECORD
