Metadata-Version: 2.4
Name: open-mcp-protocol
Version: 0.0.1
Summary: An open-source Python package for MCP (Model Context Protocol)
Project-URL: Homepage, https://github.com/2796gaurav/open-mcp
Project-URL: Documentation, https://2796gaurav.github.io/open-mcp
Project-URL: Repository, https://github.com/2796gaurav/open-mcp
Project-URL: Issues, https://github.com/2796gaurav/open-mcp/issues
Project-URL: Changelog, https://github.com/2796gaurav/open-mcp/blob/main/CHANGELOG.md
Author-email: Gaurav Chauhan <2796gaurav@gmail.com>
Maintainer-email: Gaurav Chauhan <2796gaurav@gmail.com>
License: MIT License
License-File: LICENSE
Keywords: ai,llm,mcp,model-context-protocol
Classifier: Development Status :: 3 - Alpha
Classifier: Intended Audience :: Developers
Classifier: License :: OSI Approved :: MIT License
Classifier: Operating System :: OS Independent
Classifier: Programming Language :: Python :: 3
Classifier: Programming Language :: Python :: 3.8
Classifier: Programming Language :: Python :: 3.9
Classifier: Programming Language :: Python :: 3.10
Classifier: Programming Language :: Python :: 3.11
Classifier: Programming Language :: Python :: 3.12
Classifier: Topic :: Scientific/Engineering :: Artificial Intelligence
Classifier: Topic :: Software Development :: Libraries :: Python Modules
Requires-Python: >=3.8
Requires-Dist: anyio>=3.6.0
Requires-Dist: httpx>=0.24.0
Requires-Dist: pydantic>=2.0.0
Requires-Dist: typing-extensions>=4.0.0
Provides-Extra: dev
Requires-Dist: black>=23.0.0; extra == 'dev'
Requires-Dist: isort>=5.12.0; extra == 'dev'
Requires-Dist: mypy>=1.0.0; extra == 'dev'
Requires-Dist: pre-commit>=3.0.0; extra == 'dev'
Requires-Dist: pytest-asyncio>=0.21.0; extra == 'dev'
Requires-Dist: pytest-cov>=4.0.0; extra == 'dev'
Requires-Dist: pytest>=7.0.0; extra == 'dev'
Requires-Dist: ruff>=0.1.0; extra == 'dev'
Provides-Extra: docs
Requires-Dist: mkdocs-material>=9.0.0; extra == 'docs'
Requires-Dist: mkdocs>=1.5.0; extra == 'docs'
Requires-Dist: mkdocstrings[python]>=0.23.0; extra == 'docs'
Provides-Extra: test
Requires-Dist: pytest-asyncio>=0.21.0; extra == 'test'
Requires-Dist: pytest-cov>=4.0.0; extra == 'test'
Requires-Dist: pytest>=7.0.0; extra == 'test'
Requires-Dist: respx>=0.20.0; extra == 'test'
